tungnaa/__init__.py
tungnaa/__main__.py
tungnaa/gui/__init__.py
tungnaa/gui/backend.py
tungnaa/gui/downloads.py
tungnaa/gui/qtgui.py
tungnaa/gui/senders.py
tungnaa/model.py
tungnaa/prep.py
tungnaa/resources/tungnaa_icon.png
tungnaa/resources/tungnaa_logo.png
tungnaa/split.py
tungnaa/text.py
tungnaa/train.py
tungnaa/util.py
tungnaa-0.2.0.dist-info/LICENSE
tungnaa-0.2.0.dist-info/METADATA
tungnaa-0.2.0.dist-info/WHEEL
tungnaa-0.2.0.dist-info/entry_points.txt
tungnaa-0.2.0.dist-info/RECORD
