Metadata-Version: 2.1
Name: tungnaa
Version: 0.2.0
Summary: tungnaa is a text-to-voice model family and musical instrument
License: modified GPLv3
Author: Victor Shepardson
Author-email: victor.shepardson@gmail.com
Requires-Python: >=3.10,<3.14
Classifier: License :: Other/Proprietary License
Classifier: Programming Language :: Python :: 3
Classifier: Programming Language :: Python :: 3.10
Classifier: Programming Language :: Python :: 3.11
Classifier: Programming Language :: Python :: 3.12
Provides-Extra: gui
Provides-Extra: train
Requires-Dist: PySide6 (>=6.4.3,<7.0.0,!=6.9.1) ; extra == "gui"
Requires-Dist: fire (>=0.4.0,<0.5.0)
Requires-Dist: huggingface-hub (>=0.31.4,<0.32.0)
Requires-Dist: ipykernel (>=6.29.4,<7.0.0) ; extra == "train"
Requires-Dist: markdown (>=3.8,<4.0)
Requires-Dist: markdown-full-yaml-metadata (>=2.2.1,<3.0.0)
Requires-Dist: matplotlib (>=3.7.1,<4.0.0) ; extra == "train"
Requires-Dist: normflows (>=1.7.3,<2.0.0)
Requires-Dist: numpy (<2.0.0)
Requires-Dist: odfpy (>=1.4.1,<2.0.0) ; extra == "train"
Requires-Dist: pandas (>=2.2.2,<3.0.0) ; extra == "train"
Requires-Dist: pyqtgraph (>=0.13.2,<0.14.0) ; extra == "gui"
Requires-Dist: python-osc (>=1.8.1,<2.0.0) ; extra == "gui"
Requires-Dist: scikit-learn (>=1.6.1,<2.0.0)
Requires-Dist: sounddevice (>=0.4.6,<0.5.0) ; extra == "gui"
Requires-Dist: soundfile (>=0.13.1,<0.14.0)
Requires-Dist: tensorboard (>=2.12.0,<3.0.0) ; extra == "train"
Requires-Dist: torch (>=2.6.0,<2.7.0)
Requires-Dist: torchaudio (>=2.0.0,<3.0.0) ; extra == "train"
Requires-Dist: tqdm (>=4.64,<5.0) ; extra == "train"
Requires-Dist: transformers (>=4.27.1,<5.0.0)
